manifoldbot/__init__.py
manifoldbot/cli.py
manifoldbot/ai/__init__.py
manifoldbot/ai/openai_client.py
manifoldbot/config/__init__.py
manifoldbot/config/settings.py
manifoldbot/core/__init__.py
manifoldbot/core/bot.py
manifoldbot/data/__init__.py
manifoldbot/data/sources/__init__.py
manifoldbot/examples/__init__.py
manifoldbot/examples/betsizing/bet_sizing_example.py
manifoldbot/examples/betsizing/iterative_kelly_examples.py
manifoldbot/examples/betsizing/marginal_vs_average_kelly.py
manifoldbot/examples/bot/ai_optimist_trading_bot.py
manifoldbot/examples/bot/default_users_bot.py
manifoldbot/examples/bot/generic_bot_example.py
manifoldbot/examples/bot/llm_trading_bot.py
manifoldbot/examples/comments/__init__.py
manifoldbot/examples/comments/ai_comment_example.py
manifoldbot/examples/manifold/basic_reader.py
manifoldbot/examples/manifold/basic_writer.py
manifoldbot/manifold/__init__.py
manifoldbot/manifold/bot.py
manifoldbot/manifold/comments.py
manifoldbot/manifold/lmsr.py
manifoldbot/manifold/reader.py
manifoldbot/manifold/writer.py
manifoldbot/utils/__init__.py
manifoldbot-0.2.9.dist-info/licenses/LICENSE
tests/__init__.py
tests/test_examples.py
tests/manifold/__init__.py
tests/manifold/test_bot.py
tests/manifold/test_comments.py
tests/manifold/test_lmsr.py
tests/manifold/test_market_impact.py
tests/manifold/test_reader.py
tests/manifold/test_reader_real.py
tests/manifold/test_writer.py
tests/manifold/test_writer_real.py
manifoldbot-0.2.9.dist-info/METADATA
manifoldbot-0.2.9.dist-info/WHEEL
manifoldbot-0.2.9.dist-info/entry_points.txt
manifoldbot-0.2.9.dist-info/top_level.txt
manifoldbot-0.2.9.dist-info/RECORD
